Z3Log/__init__.py
Z3Log/argument.py
Z3Log/graph.py
Z3Log/result.py
Z3Log/specs.py
Z3Log/stats.py
Z3Log/testbench.py
Z3Log/utils.py
Z3Log/verilog.py
Z3Log/z3solver.py
Z3Log/config/__init__.py
Z3Log/config/config.py
Z3Log/config/path.py
z3log-2.2.14.dist-info/LICENSE.txt
z3log-2.2.14.dist-info/METADATA
z3log-2.2.14.dist-info/WHEEL
z3log-2.2.14.dist-info/top_level.txt
z3log-2.2.14.dist-info/RECORD
