Metadata-Version: 2.1
Name: z3log
Version: 2.2.14
Summary: Paper Title: ErrorEval: an Open-Source Worst-Case-Error Evaluation Framework for Approximate Computing
Author: Morteza Rezaalipour (MorellRAP)
Author-email: <rezaalipour.usi@gmail.com>
Keywords: python,verilog,circuits,synthesis
Classifier: Development Status :: 1 - Planning
Classifier: Intended Audience :: Developers
Classifier: Programming Language :: Python :: 3
Classifier: Operating System :: Unix
Classifier: Operating System :: MacOS :: MacOS X
Classifier: Operating System :: Microsoft :: Windows
License-File: LICENSE.txt
Requires-Dist: colorama (==0.4.6)
Requires-Dist: contourpy (==1.0.6)
Requires-Dist: cycler (==0.11.0)
Requires-Dist: fonttools (==4.38.0)
Requires-Dist: kiwisolver (==1.4.4)
Requires-Dist: matplotlib (==3.6.2)
Requires-Dist: natsort (==8.2.0)
Requires-Dist: networkx (==2.8.8)
Requires-Dist: numpy (==1.24.1)
Requires-Dist: packaging (==22.0)
Requires-Dist: pandas (==1.5.2)
Requires-Dist: Pillow (==9.3.0)
Requires-Dist: pygraphviz (==1.10)
Requires-Dist: pyparsing (==3.0.9)
Requires-Dist: python-dateutil (==2.8.2)
Requires-Dist: pytz (==2022.7)
Requires-Dist: PyYAML (==6.0)
Requires-Dist: regex (==2022.10.31)
Requires-Dist: scipy (==1.9.3)
Requires-Dist: six (==1.16.0)
Requires-Dist: typing (==3.7.4.3)
Requires-Dist: z3-solver (==4.11.2.0)
